mygrations/__init__.py
mygrations/core/__init__.py
mygrations/core/commands/__init__.py
mygrations/core/commands/apply.py
mygrations/core/commands/base.py
mygrations/core/commands/check.py
mygrations/core/commands/plan.py
mygrations/core/commands/plan_export.py
mygrations/core/commands/version.py
mygrations/core/definitions/__init__.py
mygrations/core/definitions/base.py
mygrations/core/definitions/columns/__init__.py
mygrations/core/definitions/columns/column.py
mygrations/core/definitions/columns/column_test.py
mygrations/core/definitions/columns/date.py
mygrations/core/definitions/columns/enum.py
mygrations/core/definitions/columns/enum_test.py
mygrations/core/definitions/columns/numeric.py
mygrations/core/definitions/columns/numeric_test.py
mygrations/core/definitions/columns/string.py
mygrations/core/definitions/columns/string_test.py
mygrations/core/definitions/constraint.py
mygrations/core/definitions/constraint_test.py
mygrations/core/definitions/database.py
mygrations/core/definitions/index.py
mygrations/core/definitions/index_test.py
mygrations/core/definitions/option.py
mygrations/core/definitions/option_test.py
mygrations/core/definitions/rows.py
mygrations/core/definitions/table.py
mygrations/core/definitions/table_test.py
mygrations/core/operations/__init__.py
mygrations/core/operations/add_column.py
mygrations/core/operations/add_column_test.py
mygrations/core/operations/add_constraint.py
mygrations/core/operations/add_constraint_test.py
mygrations/core/operations/add_index.py
mygrations/core/operations/add_index_test.py
mygrations/core/operations/add_row.py
mygrations/core/operations/add_row_test.py
mygrations/core/operations/add_table.py
mygrations/core/operations/alter_table.py
mygrations/core/operations/alter_table_test.py
mygrations/core/operations/change_column.py
mygrations/core/operations/change_column_test.py
mygrations/core/operations/change_constraint.py
mygrations/core/operations/change_constraint_test.py
mygrations-1.0.7.dist-info/LICENSE.txt
mygrations-1.0.7.dist-info/METADATA
mygrations-1.0.7.dist-info/WHEEL
mygrations-1.0.7.dist-info/RECORD
